Metadata-Version: 2.4
Name: coconut-develop
Version: 3.2.0.post0.dev9
Summary: Simple, elegant, Pythonic functional programming.
Home-page: http://coconut-lang.org
Author: Evan Hubinger
Author-email: evanjhub@gmail.com
License: Apache-2.0
Keywords: functional,programming,language,compiler,pattern,pattern-matching,algebraic,data type,data types,lambda,lambdas,lazy,evaluation,lazy list,lazy lists,tail,recursion,call,recursive,recursive_iterator,infix,function,composition,compose,partial,application,currying,curry,pipeline,pipe,unicode,operator,operators,frozenset,literal,syntax,destructuring,assignment,fold,datamaker,prepattern,iterator,generator,none,coalesce,coalescing,statement,lru_cache,memoization,backport,typing,embed,PEP 622
Classifier: Development Status :: 5 - Production/Stable
Classifier: Intended Audience :: Developers
Classifier: Topic :: Software Development
Classifier: Topic :: Software Development :: Code Generators
Classifier: Topic :: Software Development :: Compilers
Classifier: Topic :: Software Development :: Interpreters
Classifier: Topic :: Software Development :: Libraries :: Python Modules
Classifier: Topic :: Utilities
Classifier: Environment :: Console
Classifier: Operating System :: OS Independent
Classifier: Programming Language :: Python
Classifier: Programming Language :: Python :: 2
Classifier: Programming Language :: Python :: 2.6
Classifier: Programming Language :: Python :: 2.7
Classifier: Programming Language :: Python :: 3
Classifier: Programming Language :: Python :: 3.2
Classifier: Programming Language :: Python :: 3.3
Classifier: Programming Language :: Python :: 3.4
Classifier: Programming Language :: Python :: 3.5
Classifier: Programming Language :: Python :: 3.6
Classifier: Programming Language :: Python :: 3.7
Classifier: Programming Language :: Python :: 3.8
Classifier: Programming Language :: Python :: 3.9
Classifier: Programming Language :: Python :: 3.10
Classifier: Programming Language :: Python :: 3.11
Classifier: Programming Language :: Python :: 3.12
Classifier: Programming Language :: Other
Classifier: Programming Language :: Other Scripting Engines
Classifier: Programming Language :: Python :: Implementation :: CPython
Classifier: Programming Language :: Python :: Implementation :: PyPy
Classifier: Framework :: IPython
Classifier: Framework :: Jupyter
Classifier: Typing :: Typed
License-File: LICENSE.txt
Requires-Dist: setuptools>=44
Provides-Extra: kernel
Requires-Dist: ipython>=5.4; python_version < "3" and extra == "kernel"
Requires-Dist: ipython<7.10,>=7.9; (python_version >= "3" and python_version < "3.7") and extra == "kernel"
Requires-Dist: ipython>=7.34; (python_version >= "3.7" and python_version < "3.8") and extra == "kernel"
Requires-Dist: ipython>=8.12; (python_version >= "3.8" and python_version < "3.9") and extra == "kernel"
Requires-Dist: ipython>=8.18; (python_version >= "3.9" and python_version < "3.11") and extra == "kernel"
Requires-Dist: ipython>=9; python_version >= "3.11" and extra == "kernel"
Requires-Dist: ipykernel>=4.10; python_version < "3" and extra == "kernel"
Requires-Dist: ipykernel>=5.5; (python_version >= "3" and python_version < "3.8") and extra == "kernel"
Requires-Dist: ipykernel>=6; (python_version >= "3.8" and python_version < "3.10") and extra == "kernel"
Requires-Dist: ipykernel>=7; python_version >= "3.10" and extra == "kernel"
Requires-Dist: jupyter-client>=5.3; python_version < "3.5" and extra == "kernel"
Requires-Dist: jupyter-client<6.1.13,>=6.1.12; (python_version >= "3.5" and python_version < "3.6") and extra == "kernel"
Requires-Dist: jupyter-client>=7.1.2; python_version >= "3.6" and extra == "kernel"
Requires-Dist: jedi<0.18,>=0.17; python_version < "3.9" and extra == "kernel"
Requires-Dist: jedi>=0.19; python_version >= "3.9" and extra == "kernel"
Requires-Dist: pywinpty<0.6,>=0.5; (python_version < "3" and os_name == "nt") and extra == "kernel"
Provides-Extra: watch
Requires-Dist: watchdog>=0.10; extra == "watch"
Provides-Extra: mypy
Requires-Dist: mypy[python2]>=1.19; extra == "mypy"
Requires-Dist: types-backports>=0.1; extra == "mypy"
Requires-Dist: typing>=3.10; python_version < "3.5" and extra == "mypy"
Provides-Extra: pyright
Requires-Dist: pyright>=1.1; extra == "pyright"
Requires-Dist: types-backports>=0.1; extra == "pyright"
Requires-Dist: typing>=3.10; python_version < "3.5" and extra == "pyright"
Provides-Extra: xonsh
Requires-Dist: xonsh>=0.9; python_version < "3.6" and extra == "xonsh"
Requires-Dist: xonsh>=0.11; (python_version >= "3.6" and python_version < "3.11") and extra == "xonsh"
Requires-Dist: xonsh>=0.22; python_version >= "3.11" and extra == "xonsh"
Provides-Extra: numpy
Requires-Dist: numpy>=1.16; (python_version < "3" and platform_python_implementation == "CPython") and extra == "numpy"
Requires-Dist: numpy>=1.18; (python_version >= "3.4" and python_version < "3.9") and extra == "numpy"
Requires-Dist: numpy>=1.26; python_version >= "3.9" and extra == "numpy"
Requires-Dist: pandas>=1.1; python_version >= "3.6" and extra == "numpy"
Requires-Dist: xarray>=2025; python_version >= "3.10" and extra == "numpy"
Provides-Extra: jupyter
Requires-Dist: ipython>=5.4; python_version < "3" and extra == "jupyter"
Requires-Dist: ipython<7.10,>=7.9; (python_version >= "3" and python_version < "3.7") and extra == "jupyter"
Requires-Dist: ipython>=7.34; (python_version >= "3.7" and python_version < "3.8") and extra == "jupyter"
Requires-Dist: ipython>=8.12; (python_version >= "3.8" and python_version < "3.9") and extra == "jupyter"
Requires-Dist: ipython>=8.18; (python_version >= "3.9" and python_version < "3.11") and extra == "jupyter"
Requires-Dist: ipython>=9; python_version >= "3.11" and extra == "jupyter"
Requires-Dist: ipykernel>=4.10; python_version < "3" and extra == "jupyter"
Requires-Dist: ipykernel>=5.5; (python_version >= "3" and python_version < "3.8") and extra == "jupyter"
Requires-Dist: ipykernel>=6; (python_version >= "3.8" and python_version < "3.10") and extra == "jupyter"
Requires-Dist: ipykernel>=7; python_version >= "3.10" and extra == "jupyter"
Requires-Dist: jupyter-client>=5.3; python_version < "3.5" and extra == "jupyter"
Requires-Dist: jupyter-client<6.1.13,>=6.1.12; (python_version >= "3.5" and python_version < "3.6") and extra == "jupyter"
Requires-Dist: jupyter-client>=7.1.2; python_version >= "3.6" and extra == "jupyter"
Requires-Dist: jedi<0.18,>=0.17; python_version < "3.9" and extra == "jupyter"
Requires-Dist: jedi>=0.19; python_version >= "3.9" and extra == "jupyter"
Requires-Dist: pywinpty<0.6,>=0.5; (python_version < "3" and os_name == "nt") and extra == "jupyter"
Requires-Dist: jupyter>=1.1; extra == "jupyter"
Requires-Dist: jupyter-console>=5.2; python_version < "3.5" and extra == "jupyter"
Requires-Dist: jupyter-console>=6.1; (python_version >= "3.5" and python_version < "3.7") and extra == "jupyter"
Requires-Dist: jupyter-console>=6.6; python_version >= "3.7" and extra == "jupyter"
Requires-Dist: papermill>=1.2; extra == "jupyter"
Provides-Extra: jupyterlab
Requires-Dist: ipython>=5.4; python_version < "3" and extra == "jupyterlab"
Requires-Dist: ipython<7.10,>=7.9; (python_version >= "3" and python_version < "3.7") and extra == "jupyterlab"
Requires-Dist: ipython>=7.34; (python_version >= "3.7" and python_version < "3.8") and extra == "jupyterlab"
Requires-Dist: ipython>=8.12; (python_version >= "3.8" and python_version < "3.9") and extra == "jupyterlab"
Requires-Dist: ipython>=8.18; (python_version >= "3.9" and python_version < "3.11") and extra == "jupyterlab"
Requires-Dist: ipython>=9; python_version >= "3.11" and extra == "jupyterlab"
Requires-Dist: ipykernel>=4.10; python_version < "3" and extra == "jupyterlab"
Requires-Dist: ipykernel>=5.5; (python_version >= "3" and python_version < "3.8") and extra == "jupyterlab"
Requires-Dist: ipykernel>=6; (python_version >= "3.8" and python_version < "3.10") and extra == "jupyterlab"
Requires-Dist: ipykernel>=7; python_version >= "3.10" and extra == "jupyterlab"
Requires-Dist: jupyter-client>=5.3; python_version < "3.5" and extra == "jupyterlab"
Requires-Dist: jupyter-client<6.1.13,>=6.1.12; (python_version >= "3.5" and python_version < "3.6") and extra == "jupyterlab"
Requires-Dist: jupyter-client>=7.1.2; python_version >= "3.6" and extra == "jupyterlab"
Requires-Dist: jedi<0.18,>=0.17; python_version < "3.9" and extra == "jupyterlab"
Requires-Dist: jedi>=0.19; python_version >= "3.9" and extra == "jupyterlab"
Requires-Dist: pywinpty<0.6,>=0.5; (python_version < "3" and os_name == "nt") and extra == "jupyterlab"
Requires-Dist: jupyter>=1.1; extra == "jupyterlab"
Requires-Dist: jupyter-console>=5.2; python_version < "3.5" and extra == "jupyterlab"
Requires-Dist: jupyter-console>=6.1; (python_version >= "3.5" and python_version < "3.7") and extra == "jupyterlab"
Requires-Dist: jupyter-console>=6.6; python_version >= "3.7" and extra == "jupyterlab"
Requires-Dist: papermill>=1.2; extra == "jupyterlab"
Requires-Dist: jupyterlab>=2.2; python_version >= "3.5" and extra == "jupyterlab"
Provides-Extra: jupytext
Requires-Dist: ipython>=5.4; python_version < "3" and extra == "jupytext"
Requires-Dist: ipython<7.10,>=7.9; (python_version >= "3" and python_version < "3.7") and extra == "jupytext"
Requires-Dist: ipython>=7.34; (python_version >= "3.7" and python_version < "3.8") and extra == "jupytext"
Requires-Dist: ipython>=8.12; (python_version >= "3.8" and python_version < "3.9") and extra == "jupytext"
Requires-Dist: ipython>=8.18; (python_version >= "3.9" and python_version < "3.11") and extra == "jupytext"
Requires-Dist: ipython>=9; python_version >= "3.11" and extra == "jupytext"
Requires-Dist: ipykernel>=4.10; python_version < "3" and extra == "jupytext"
Requires-Dist: ipykernel>=5.5; (python_version >= "3" and python_version < "3.8") and extra == "jupytext"
Requires-Dist: ipykernel>=6; (python_version >= "3.8" and python_version < "3.10") and extra == "jupytext"
Requires-Dist: ipykernel>=7; python_version >= "3.10" and extra == "jupytext"
Requires-Dist: jupyter-client>=5.3; python_version < "3.5" and extra == "jupytext"
Requires-Dist: jupyter-client<6.1.13,>=6.1.12; (python_version >= "3.5" and python_version < "3.6") and extra == "jupytext"
Requires-Dist: jupyter-client>=7.1.2; python_version >= "3.6" and extra == "jupytext"
Requires-Dist: jedi<0.18,>=0.17; python_version < "3.9" and extra == "jupytext"
Requires-Dist: jedi>=0.19; python_version >= "3.9" and extra == "jupytext"
Requires-Dist: pywinpty<0.6,>=0.5; (python_version < "3" and os_name == "nt") and extra == "jupytext"
Requires-Dist: jupyter>=1.1; extra == "jupytext"
Requires-Dist: jupyter-console>=5.2; python_version < "3.5" and extra == "jupytext"
Requires-Dist: jupyter-console>=6.1; (python_version >= "3.5" and python_version < "3.7") and extra == "jupytext"
Requires-Dist: jupyter-console>=6.6; python_version >= "3.7" and extra == "jupytext"
Requires-Dist: papermill>=1.2; extra == "jupytext"
Requires-Dist: jupytext>=1.8; python_version >= "3" and extra == "jupytext"
Provides-Extra: all
Requires-Dist: ipython>=5.4; python_version < "3" and extra == "all"
Requires-Dist: ipython<7.10,>=7.9; (python_version >= "3" and python_version < "3.7") and extra == "all"
Requires-Dist: ipython>=7.34; (python_version >= "3.7" and python_version < "3.8") and extra == "all"
Requires-Dist: ipython>=8.12; (python_version >= "3.8" and python_version < "3.9") and extra == "all"
Requires-Dist: ipython>=8.18; (python_version >= "3.9" and python_version < "3.11") and extra == "all"
Requires-Dist: ipython>=9; python_version >= "3.11" and extra == "all"
Requires-Dist: ipykernel>=4.10; python_version < "3" and extra == "all"
Requires-Dist: ipykernel>=5.5; (python_version >= "3" and python_version < "3.8") and extra == "all"
Requires-Dist: ipykernel>=6; (python_version >= "3.8" and python_version < "3.10") and extra == "all"
Requires-Dist: ipykernel>=7; python_version >= "3.10" and extra == "all"
Requires-Dist: jupyter-client>=5.3; python_version < "3.5" and extra == "all"
Requires-Dist: jupyter-client<6.1.13,>=6.1.12; (python_version >= "3.5" and python_version < "3.6") and extra == "all"
Requires-Dist: jupyter-client>=7.1.2; python_version >= "3.6" and extra == "all"
Requires-Dist: jedi<0.18,>=0.17; python_version < "3.9" and extra == "all"
Requires-Dist: jedi>=0.19; python_version >= "3.9" and extra == "all"
Requires-Dist: pywinpty<0.6,>=0.5; (python_version < "3" and os_name == "nt") and extra == "all"
Requires-Dist: watchdog>=0.10; extra == "all"
Requires-Dist: mypy[python2]>=1.19; extra == "all"
Requires-Dist: types-backports>=0.1; extra == "all"
Requires-Dist: typing>=3.10; python_version < "3.5" and extra == "all"
Requires-Dist: pyright>=1.1; extra == "all"
Requires-Dist: xonsh>=0.9; python_version < "3.6" and extra == "all"
Requires-Dist: xonsh>=0.11; (python_version >= "3.6" and python_version < "3.11") and extra == "all"
Requires-Dist: xonsh>=0.22; python_version >= "3.11" and extra == "all"
Requires-Dist: numpy>=1.16; (python_version < "3" and platform_python_implementation == "CPython") and extra == "all"
Requires-Dist: numpy>=1.18; (python_version >= "3.4" and python_version < "3.9") and extra == "all"
Requires-Dist: numpy>=1.26; python_version >= "3.9" and extra == "all"
Requires-Dist: pandas>=1.1; python_version >= "3.6" and extra == "all"
Requires-Dist: xarray>=2025; python_version >= "3.10" and extra == "all"
Requires-Dist: jupyter>=1.1; extra == "all"
Requires-Dist: jupyter-console>=5.2; python_version < "3.5" and extra == "all"
Requires-Dist: jupyter-console>=6.1; (python_version >= "3.5" and python_version < "3.7") and extra == "all"
Requires-Dist: jupyter-console>=6.6; python_version >= "3.7" and extra == "all"
Requires-Dist: papermill>=1.2; extra == "all"
Requires-Dist: jupyterlab>=2.2; python_version >= "3.5" and extra == "all"
Requires-Dist: jupytext>=1.8; python_version >= "3" and extra == "all"
Provides-Extra: ipython
Requires-Dist: ipython>=5.4; python_version < "3" and extra == "ipython"
Requires-Dist: ipython<7.10,>=7.9; (python_version >= "3" and python_version < "3.7") and extra == "ipython"
Requires-Dist: ipython>=7.34; (python_version >= "3.7" and python_version < "3.8") and extra == "ipython"
Requires-Dist: ipython>=8.12; (python_version >= "3.8" and python_version < "3.9") and extra == "ipython"
Requires-Dist: ipython>=8.18; (python_version >= "3.9" and python_version < "3.11") and extra == "ipython"
Requires-Dist: ipython>=9; python_version >= "3.11" and extra == "ipython"
Requires-Dist: ipykernel>=4.10; python_version < "3" and extra == "ipython"
Requires-Dist: ipykernel>=5.5; (python_version >= "3" and python_version < "3.8") and extra == "ipython"
Requires-Dist: ipykernel>=6; (python_version >= "3.8" and python_version < "3.10") and extra == "ipython"
Requires-Dist: ipykernel>=7; python_version >= "3.10" and extra == "ipython"
Requires-Dist: jupyter-client>=5.3; python_version < "3.5" and extra == "ipython"
Requires-Dist: jupyter-client<6.1.13,>=6.1.12; (python_version >= "3.5" and python_version < "3.6") and extra == "ipython"
Requires-Dist: jupyter-client>=7.1.2; python_version >= "3.6" and extra == "ipython"
Requires-Dist: jedi<0.18,>=0.17; python_version < "3.9" and extra == "ipython"
Requires-Dist: jedi>=0.19; python_version >= "3.9" and extra == "ipython"
Requires-Dist: pywinpty<0.6,>=0.5; (python_version < "3" and os_name == "nt") and extra == "ipython"
Requires-Dist: jupyter>=1.1; extra == "ipython"
Requires-Dist: jupyter-console>=5.2; python_version < "3.5" and extra == "ipython"
Requires-Dist: jupyter-console>=6.1; (python_version >= "3.5" and python_version < "3.7") and extra == "ipython"
Requires-Dist: jupyter-console>=6.6; python_version >= "3.7" and extra == "ipython"
Requires-Dist: papermill>=1.2; extra == "ipython"
Provides-Extra: docs
Requires-Dist: sphinx>=8; extra == "docs"
Requires-Dist: pygments>=2.3; python_version < "3.9" and extra == "docs"
Requires-Dist: pygments>=2.19; python_version >= "3.9" and extra == "docs"
Requires-Dist: myst-parser>=4; extra == "docs"
Requires-Dist: pydata-sphinx-theme>=0.16; extra == "docs"
Requires-Dist: sphinxcontrib_applehelp>=2; extra == "docs"
Requires-Dist: sphinxcontrib_htmlhelp>=2; extra == "docs"
Provides-Extra: tests
Requires-Dist: pytest>=3; python_version < "3.6" and extra == "tests"
Requires-Dist: pytest>=7; (python_version >= "3.6" and python_version < "3.8") and extra == "tests"
Requires-Dist: pytest<8.1,>=8.0; python_version >= "3.8" and extra == "tests"
Requires-Dist: pexpect>=4; extra == "tests"
Requires-Dist: pytest_remotedata>=0.3; extra == "tests"
Requires-Dist: ipython>=5.4; python_version < "3" and extra == "tests"
Requires-Dist: ipython<7.10,>=7.9; (python_version >= "3" and python_version < "3.7") and extra == "tests"
Requires-Dist: ipython>=7.34; (python_version >= "3.7" and python_version < "3.8") and extra == "tests"
Requires-Dist: ipython>=8.12; (python_version >= "3.8" and python_version < "3.9") and extra == "tests"
Requires-Dist: ipython>=8.18; (python_version >= "3.9" and python_version < "3.11") and extra == "tests"
Requires-Dist: ipython>=9; python_version >= "3.11" and extra == "tests"
Requires-Dist: ipykernel>=4.10; python_version < "3" and extra == "tests"
Requires-Dist: ipykernel>=5.5; (python_version >= "3" and python_version < "3.8") and extra == "tests"
Requires-Dist: ipykernel>=6; (python_version >= "3.8" and python_version < "3.10") and extra == "tests"
Requires-Dist: ipykernel>=7; python_version >= "3.10" and extra == "tests"
Requires-Dist: jupyter-client>=5.3; python_version < "3.5" and extra == "tests"
Requires-Dist: jupyter-client<6.1.13,>=6.1.12; (python_version >= "3.5" and python_version < "3.6") and extra == "tests"
Requires-Dist: jupyter-client>=7.1.2; python_version >= "3.6" and extra == "tests"
Requires-Dist: jedi<0.18,>=0.17; python_version < "3.9" and extra == "tests"
Requires-Dist: jedi>=0.19; python_version >= "3.9" and extra == "tests"
Requires-Dist: pywinpty<0.6,>=0.5; (python_version < "3" and os_name == "nt") and extra == "tests"
Requires-Dist: jupyter>=1.1; extra == "tests"
Requires-Dist: jupyter-console>=5.2; python_version < "3.5" and extra == "tests"
Requires-Dist: jupyter-console>=6.1; (python_version >= "3.5" and python_version < "3.7") and extra == "tests"
Requires-Dist: jupyter-console>=6.6; python_version >= "3.7" and extra == "tests"
Requires-Dist: papermill>=1.2; extra == "tests"
Provides-Extra: dev
Requires-Dist: ipython>=5.4; python_version < "3" and extra == "dev"
Requires-Dist: ipython<7.10,>=7.9; (python_version >= "3" and python_version < "3.7") and extra == "dev"
Requires-Dist: ipython>=7.34; (python_version >= "3.7" and python_version < "3.8") and extra == "dev"
Requires-Dist: ipython>=8.12; (python_version >= "3.8" and python_version < "3.9") and extra == "dev"
Requires-Dist: ipython>=8.18; (python_version >= "3.9" and python_version < "3.11") and extra == "dev"
Requires-Dist: ipython>=9; python_version >= "3.11" and extra == "dev"
Requires-Dist: ipykernel>=4.10; python_version < "3" and extra == "dev"
Requires-Dist: ipykernel>=5.5; (python_version >= "3" and python_version < "3.8") and extra == "dev"
Requires-Dist: ipykernel>=6; (python_version >= "3.8" and python_version < "3.10") and extra == "dev"
Requires-Dist: ipykernel>=7; python_version >= "3.10" and extra == "dev"
Requires-Dist: jupyter-client>=5.3; python_version < "3.5" and extra == "dev"
Requires-Dist: jupyter-client<6.1.13,>=6.1.12; (python_version >= "3.5" and python_version < "3.6") and extra == "dev"
Requires-Dist: jupyter-client>=7.1.2; python_version >= "3.6" and extra == "dev"
Requires-Dist: jedi<0.18,>=0.17; python_version < "3.9" and extra == "dev"
Requires-Dist: jedi>=0.19; python_version >= "3.9" and extra == "dev"
Requires-Dist: pywinpty<0.6,>=0.5; (python_version < "3" and os_name == "nt") and extra == "dev"
Requires-Dist: watchdog>=0.10; extra == "dev"
Requires-Dist: mypy[python2]>=1.19; extra == "dev"
Requires-Dist: types-backports>=0.1; extra == "dev"
Requires-Dist: typing>=3.10; python_version < "3.5" and extra == "dev"
Requires-Dist: pyright>=1.1; extra == "dev"
Requires-Dist: xonsh>=0.9; python_version < "3.6" and extra == "dev"
Requires-Dist: xonsh>=0.11; (python_version >= "3.6" and python_version < "3.11") and extra == "dev"
Requires-Dist: xonsh>=0.22; python_version >= "3.11" and extra == "dev"
Requires-Dist: numpy>=1.16; (python_version < "3" and platform_python_implementation == "CPython") and extra == "dev"
Requires-Dist: numpy>=1.18; (python_version >= "3.4" and python_version < "3.9") and extra == "dev"
Requires-Dist: numpy>=1.26; python_version >= "3.9" and extra == "dev"
Requires-Dist: pandas>=1.1; python_version >= "3.6" and extra == "dev"
Requires-Dist: xarray>=2025; python_version >= "3.10" and extra == "dev"
Requires-Dist: jupyter>=1.1; extra == "dev"
Requires-Dist: jupyter-console>=5.2; python_version < "3.5" and extra == "dev"
Requires-Dist: jupyter-console>=6.1; (python_version >= "3.5" and python_version < "3.7") and extra == "dev"
Requires-Dist: jupyter-console>=6.6; python_version >= "3.7" and extra == "dev"
Requires-Dist: papermill>=1.2; extra == "dev"
Requires-Dist: jupyterlab>=2.2; python_version >= "3.5" and extra == "dev"
Requires-Dist: jupytext>=1.8; python_version >= "3" and extra == "dev"
Requires-Dist: sphinx>=8; extra == "dev"
Requires-Dist: pygments>=2.3; python_version < "3.9" and extra == "dev"
Requires-Dist: pygments>=2.19; python_version >= "3.9" and extra == "dev"
Requires-Dist: myst-parser>=4; extra == "dev"
Requires-Dist: pydata-sphinx-theme>=0.16; extra == "dev"
Requires-Dist: sphinxcontrib_applehelp>=2; extra == "dev"
Requires-Dist: sphinxcontrib_htmlhelp>=2; extra == "dev"
Requires-Dist: pytest>=3; python_version < "3.6" and extra == "dev"
Requires-Dist: pytest>=7; (python_version >= "3.6" and python_version < "3.8") and extra == "dev"
Requires-Dist: pytest<8.1,>=8.0; python_version >= "3.8" and extra == "dev"
Requires-Dist: pexpect>=4; extra == "dev"
Requires-Dist: pytest_remotedata>=0.3; extra == "dev"
Requires-Dist: pyparsing<2.4.8,>=2.4.7; extra == "dev"
Requires-Dist: pre-commit>=4; python_version >= "3" and extra == "dev"
Requires-Dist: requests>=2.32; extra == "dev"
Requires-Dist: vprof>=0.36; extra == "dev"
Requires-Dist: py-spy>=0.4; extra == "dev"
Requires-Dist: argparse>=1.4; python_version < "2.7"
Requires-Dist: psutil>=6; python_version >= "2.7" and python_version < "3"
Requires-Dist: psutil>=7; python_version >= "3"
Requires-Dist: prompt_toolkit>=1; python_version >= "3"
Requires-Dist: futures>=3.4; python_version < "3"
Requires-Dist: backports.functools-lru-cache>=1.6; python_version < "3"
Requires-Dist: prompt_toolkit<2,>=1; python_version < "3"
Requires-Dist: pygments>=2.3; python_version < "3.9"
Requires-Dist: pygments>=2.19; python_version >= "3.9"
Requires-Dist: typing_extensions>=4.15; python_version >= "3.9"
Requires-Dist: typing_extensions>=3.10; python_version < "3.6"
Requires-Dist: typing_extensions>=4.1; python_version >= "3.6" and python_version < "3.7"
Requires-Dist: dataclasses>=0.8; python_version >= "3.6" and python_version < "3.7"
Requires-Dist: typing_extensions>=4.7; python_version >= "3.7" and python_version < "3.8"
Requires-Dist: typing_extensions>=4.12; python_version >= "3.8" and python_version < "3.9"
Requires-Dist: trollius>=2.2; python_version < "3" and platform_python_implementation == "CPython"
Requires-Dist: aenum>=3.1.16; python_version < "3.4"
Requires-Dist: typing>=3.10; python_version < "3.5"
Requires-Dist: async_generator>=1.10; python_version >= "3.5"
Requires-Dist: tstr>=0.4; python_version >= "3.10"
Requires-Dist: exceptiongroup>=1; python_version >= "3.7" and python_version < "3.11"
Requires-Dist: anyio>=3; python_version >= "3.6"
Requires-Dist: cPyparsing<2.4.7.2.5,>=2.4.7.2.4.1; platform_python_implementation == "CPython"
Requires-Dist: pyparsing<2.4.8,>=2.4.7; platform_python_implementation != "CPython"
Dynamic: author
Dynamic: author-email
Dynamic: classifier
Dynamic: description
Dynamic: home-page
Dynamic: keywords
Dynamic: license
Dynamic: license-file
Dynamic: provides-extra
Dynamic: requires-dist
Dynamic: summary
